cookiecutter_fastapi_backend-2.3.0.dist-info/licenses/AUTHORS
cookiecutter_fastapi_backend-2.3.0.dist-info/licenses/LICENSE
hooks/post_gen_project.py
hooks/pre_gen_project.py
cookiecutter_fastapi_backend-2.3.0.dist-info/METADATA
cookiecutter_fastapi_backend-2.3.0.dist-info/WHEEL
cookiecutter_fastapi_backend-2.3.0.dist-info/top_level.txt
cookiecutter_fastapi_backend-2.3.0.dist-info/RECORD
