Metadata-Version: 2.4
Name: cookiecutter-fastapi-backend
Version: 2.3.0
Summary: Cookiecutter template to build and deploy fastapi backends..batteries included
Author-email: nickatnight <nialexanderke@proton.me>
Project-URL: Homepage, https://github.com/nickatnight/cookiecutter-fastapi-backend
Project-URL: Repository, https://github.com/nickatnight/cookiecutter-fastapi-backend
Classifier: Framework :: FastAPI
Classifier: Intended Audience :: Developers
Classifier: Programming Language :: Python :: 3
Classifier: Programming Language :: Python :: 3.10
Classifier: Programming Language :: Python :: 3.11
Classifier: Programming Language :: Python :: 3.12
Classifier: Programming Language :: Python :: 3.13
Classifier: Topic :: Software Development :: Code Generators
Requires-Python: >=3.9
License-File: LICENSE
License-File: AUTHORS
Requires-Dist: cookiecutter==2.6.0
Dynamic: license-file
